{
  "nodes": {
    "1102038262": [
      59.9350729,
      30.2970328
    ],
    "1102038267": [
      59.9349202,
      30.2970135
    ],
    "1102038311": [
      59.9343631,
      30.2975839
    ],
    "1102038342": [
      59.9349355,
      30.2970714
    ],
    "1102038397": [
      59.9344461,
      30.2974829
    ],
    "1102038569": [
      59.934688,
      30.2972977
    ],
    "1102038627": [
      59.9346659,
      30.2972155
    ],
    "1102038699": [
      59.9344847,
      30.2976041
    ],
    "1102038707": [
      59.9344284,
      30.2978011
    ],
    "1102038744": [
      59.934994,
      30.2968162
    ],
    "3625611706": [
      59.9350431,
      30.2969509
    ],
    "4174201167": [
      59.9343719,
      30.2976131
    ],
    "4174201168": [
      59.9344137,
      30.2977523
    ]
  },
  "ways": {
    "94946491": {
      "nodes": [
        [
          59.9350729,
          30.2970328
        ],
        [
          59.9344284,
          30.2978011
        ],
        [
          59.9344137,
          30.2977523
        ],
        [
          59.9343719,
          30.2976131
        ],
        [
          59.9343631,
          30.2975839
        ],
        [
          59.9344461,
          30.2974829
        ],
        [
          59.9344847,
          30.2976041
        ],
        [
          59.9349355,
          30.2970714
        ],
        [
          59.9349202,
          30.2970135
        ],
        [
          59.934688,
          30.2972977
        ],
        [
          59.9346659,
          30.2972155
        ],
        [
          59.934994,
          30.2968162
        ],
        [
          59.9350431,
          30.2969509
        ],
        [
          59.9350729,
          30.2970328
        ]
      ],
      "oldName": "Шамберлинъ, Маргариты, дочери Английскаго купца"
    }
  },
  "relations": []
}