<?xml version="1.0" encoding="UTF-8"?>
<osm version="0.6" generator="CGImap 0.9.2 (187089 spike-06.openstreetmap.org)" copyright="OpenStreetMap and contributors" attribution="http://www.openstreetmap.org/copyright" license="http://opendatacommons.org/licenses/odbl/1-0/">
 <node id="1102038173" visible="true" version="3" changeset="63736522" timestamp="2018-10-21T19:23:44Z" user="mini-me" uid="3846961" lat="59.9357390" lon="30.3009015"/>
 <node id="1102038188" visible="true" version="3" changeset="60233132" timestamp="2018-06-28T02:51:12Z" user="Anton Khorev" uid="437809" lat="59.9352358" lon="30.3004891"/>
 <node id="1102038189" visible="true" version="3" changeset="63736522" timestamp="2018-10-21T19:23:44Z" user="mini-me" uid="3846961" lat="59.9359069" lon="30.3004805"/>
 <node id="1102038192" visible="true" version="1" changeset="6957401" timestamp="2011-01-13T14:00:35Z" user="KonTur" uid="43262" lat="59.9362440" lon="30.3006940"/>
 <node id="1102038194" visible="true" version="2" changeset="60233132" timestamp="2018-06-28T02:51:12Z" user="Anton Khorev" uid="437809" lat="59.9360327" lon="30.3006164"/>
 <node id="1102038216" visible="true" version="3" changeset="63736522" timestamp="2018-10-21T19:23:43Z" user="mini-me" uid="3846961" lat="59.9357018" lon="30.3002812"/>
 <node id="1102038219" visible="true" version="2" changeset="60233132" timestamp="2018-06-28T02:51:12Z" user="Anton Khorev" uid="437809" lat="59.9357841" lon="30.3007775"/>
 <node id="1102038231" visible="true" version="3" changeset="63736522" timestamp="2018-10-21T19:23:44Z" user="mini-me" uid="3846961" lat="59.9359098" lon="30.3006594"/>
 <node id="1102038235" visible="true" version="1" changeset="6957401" timestamp="2011-01-13T14:00:37Z" user="KonTur" uid="43262" lat="59.9362664" lon="30.3006132"/>
 <node id="1102038238" visible="true" version="3" changeset="63736522" timestamp="2018-10-21T19:23:43Z" user="mini-me" uid="3846961" lat="59.9359756" lon="30.3001202"/>
 <node id="1102038256" visible="true" version="3" changeset="63736522" timestamp="2018-10-21T19:23:44Z" user="mini-me" uid="3846961" lat="59.9356469" lon="30.3002003"/>
 <node id="1102038258" visible="true" version="3" changeset="63736522" timestamp="2018-10-21T19:23:43Z" user="mini-me" uid="3846961" lat="59.9355623" lon="30.3006244"/>
 <node id="1102038273" visible="true" version="2" changeset="7725026" timestamp="2011-03-31T11:00:44Z" user="fserges" uid="368493" lat="59.9359448" lon="30.2994820"/>
 <node id="1102038279" visible="true" version="3" changeset="63736522" timestamp="2018-10-21T19:23:44Z" user="mini-me" uid="3846961" lat="59.9359861" lon="30.3005762"/>
 <node id="1102038294" visible="true" version="3" changeset="63736522" timestamp="2018-10-21T19:23:44Z" user="mini-me" uid="3846961" lat="59.9358996" lon="30.3004028"/>
 <node id="1102038298" visible="true" version="3" changeset="63736522" timestamp="2018-10-21T19:23:43Z" user="mini-me" uid="3846961" lat="59.9355635" lon="30.3004822"/>
 <node id="1102038302" visible="true" version="2" changeset="60233132" timestamp="2018-06-28T02:51:12Z" user="Anton Khorev" uid="437809" lat="59.9356820" lon="30.3007145"/>
 <node id="1102038320" visible="true" version="3" changeset="63736522" timestamp="2018-10-21T19:23:44Z" user="mini-me" uid="3846961" lat="59.9359628" lon="30.3005897"/>
 <node id="1102038339" visible="true" version="2" changeset="60233132" timestamp="2018-06-28T02:51:12Z" user="Anton Khorev" uid="437809" lat="59.9357392" lon="30.3007800"/>
 <node id="1102038346" visible="true" version="3" changeset="63736522" timestamp="2018-10-21T19:23:44Z" user="mini-me" uid="3846961" lat="59.9356842" lon="30.3003073"/>
 <node id="1102038352" visible="true" version="1" changeset="6957401" timestamp="2011-01-13T14:00:41Z" user="KonTur" uid="43262" lat="59.9359585" lon="30.2994624"/>
 <node id="1102038360" visible="true" version="2" changeset="60233132" timestamp="2018-06-28T02:51:12Z" user="Anton Khorev" uid="437809" lat="59.9360928" lon="30.3004947"/>
 <node id="1102038368" visible="true" version="2" changeset="60233132" timestamp="2018-06-28T02:51:12Z" user="Anton Khorev" uid="437809" lat="59.9357208" lon="30.3009764"/>
 <node id="1102038390" visible="true" version="3" changeset="63736522" timestamp="2018-10-21T19:23:44Z" user="mini-me" uid="3846961" lat="59.9359019" lon="30.3005508"/>
 <node id="1102038394" visible="true" version="2" changeset="60233132" timestamp="2018-06-28T02:51:12Z" user="Anton Khorev" uid="437809" lat="59.9357279" lon="30.3009312"/>
 <node id="1102038411" visible="true" version="3" changeset="63736522" timestamp="2018-10-21T19:23:44Z" user="mini-me" uid="3846961" lat="59.9355538" lon="30.3008911"/>
 <node id="1102038430" visible="true" version="2" changeset="7725026" timestamp="2011-03-31T11:00:48Z" user="fserges" uid="368493" lat="59.9354878" lon="30.3001365"/>
 <node id="1102038434" visible="true" version="3" changeset="63736522" timestamp="2018-10-21T19:23:43Z" user="mini-me" uid="3846961" lat="59.9358166" lon="30.3001154"/>
 <node id="1102038441" visible="true" version="3" changeset="63736522" timestamp="2018-10-21T19:23:44Z" user="mini-me" uid="3846961" lat="59.9357990" lon="30.3008175"/>
 <node id="1102038463" visible="true" version="3" changeset="63736522" timestamp="2018-10-21T19:23:44Z" user="mini-me" uid="3846961" lat="59.9358910" lon="30.3006118"/>
 <node id="1102038469" visible="true" version="1" changeset="6957401" timestamp="2011-01-13T14:00:44Z" user="KonTur" uid="43262" lat="59.9362802" lon="30.3004586"/>
 <node id="1102038477" visible="true" version="3" changeset="63736522" timestamp="2018-10-21T19:23:44Z" user="mini-me" uid="3846961" lat="59.9360146" lon="30.3002339"/>
 <node id="1102038481" visible="true" version="3" changeset="63736522" timestamp="2018-10-21T19:23:43Z" user="mini-me" uid="3846961" lat="59.9355200" lon="30.3007677"/>
 <node id="1102038497" visible="true" version="1" changeset="6957401" timestamp="2011-01-13T14:00:45Z" user="KonTur" uid="43262" lat="59.9362693" lon="30.3003304"/>
 <node id="1102038501" visible="true" version="3" changeset="63736522" timestamp="2018-10-21T19:23:43Z" user="mini-me" uid="3846961" lat="59.9355822" lon="30.3006820"/>
 <node id="1102038524" visible="true" version="1" changeset="6957401" timestamp="2011-01-13T14:00:46Z" user="KonTur" uid="43262" lat="59.9362138" lon="30.3007650"/>
 <node id="1102038526" visible="true" version="3" changeset="63736522" timestamp="2018-10-21T19:23:44Z" user="mini-me" uid="3846961" lat="59.9356651" lon="30.3001803"/>
 <node id="1102038539" visible="true" version="2" changeset="60233132" timestamp="2018-06-28T02:51:12Z" user="Anton Khorev" uid="437809" lat="59.9360864" lon="30.3004399"/>
 <node id="1102038564" visible="true" version="3" changeset="63736522" timestamp="2018-10-21T19:23:43Z" user="mini-me" uid="3846961" lat="59.9355964" lon="30.3005773"/>
 <node id="1102038589" visible="true" version="2" changeset="7725026" timestamp="2011-03-31T11:00:49Z" user="fserges" uid="368493" lat="59.9354645" lon="30.3001698"/>
 <node id="1102038592" visible="true" version="3" changeset="63736522" timestamp="2018-10-21T19:23:44Z" user="mini-me" uid="3846961" lat="59.9360110" lon="30.3005898"/>
 <node id="1102038621" visible="true" version="2" changeset="60233132" timestamp="2018-06-28T02:51:12Z" user="Anton Khorev" uid="437809" lat="59.9357622" lon="30.3007831"/>
 <node id="1102038629" visible="true" version="3" changeset="63736522" timestamp="2018-10-21T19:23:44Z" user="mini-me" uid="3846961" lat="59.9356367" lon="30.3011810"/>
 <node id="1102038640" visible="true" version="4" changeset="60233132" timestamp="2018-06-28T02:51:12Z" user="Anton Khorev" uid="437809" lat="59.9355822" lon="30.3017121"/>
 <node id="1102038663" visible="true" version="2" changeset="60233132" timestamp="2018-06-28T02:51:12Z" user="Anton Khorev" uid="437809" lat="59.9360828" lon="30.3005455"/>
 <node id="1102038691" visible="true" version="3" changeset="63736522" timestamp="2018-10-21T19:23:43Z" user="mini-me" uid="3846961" lat="59.9358662" lon="30.2998186"/>
 <node id="1102038697" visible="true" version="2" changeset="60233132" timestamp="2018-06-28T02:51:12Z" user="Anton Khorev" uid="437809" lat="59.9357095" lon="30.3007603"/>
 <node id="1102038705" visible="true" version="3" changeset="63736522" timestamp="2018-10-21T19:23:44Z" user="mini-me" uid="3846961" lat="59.9354097" lon="30.3004490"/>
 <node id="1102038729" visible="true" version="2" changeset="60233132" timestamp="2018-06-28T02:51:12Z" user="Anton Khorev" uid="437809" lat="59.9357234" lon="30.3010629"/>
 <node id="1102038741" visible="true" version="3" changeset="63736522" timestamp="2018-10-21T19:23:43Z" user="mini-me" uid="3846961" lat="59.9359025" lon="30.3002258"/>
 <node id="1606512665" visible="true" version="1" changeset="10503407" timestamp="2012-01-26T13:57:27Z" user="Anton Khorev" uid="437809" lat="59.9358979" lon="30.3012111">
  <tag k="entrance" v="main"/>
 </node>
 <node id="3625611709" visible="true" version="1" changeset="32291125" timestamp="2015-06-29T18:24:37Z" user="EIjas" uid="700550" lat="59.9362506" lon="30.3002783">
  <tag k="addr:housenumber" v="2"/>
  <tag k="addr:street" v="Английская набережная"/>
 </node>
 <node id="3625629670" visible="true" version="3" changeset="60233132" timestamp="2018-06-28T02:51:14Z" user="Anton Khorev" uid="437809" lat="59.9355454" lon="30.3015894">
  <tag k="addr:housenumber" v="1"/>
  <tag k="addr:street" v="Галерная улица"/>
 </node>
 <node id="3625629684" visible="true" version="3" changeset="60233132" timestamp="2018-06-28T02:51:15Z" user="Anton Khorev" uid="437809" lat="59.9355324" lon="30.3015461"/>
 <node id="3811443089" visible="true" version="2" changeset="60233132" timestamp="2018-06-28T02:51:15Z" user="Anton Khorev" uid="437809" lat="59.9355471" lon="30.3015255"/>
 <node id="3811443090" visible="true" version="1" changeset="34997389" timestamp="2015-10-31T18:09:15Z" user="yuryleb" uid="446083" lat="59.9357406" lon="30.3014315"/>
 <node id="3811443091" visible="true" version="1" changeset="34997389" timestamp="2015-10-31T18:09:15Z" user="yuryleb" uid="446083" lat="59.9357303" lon="30.3014992"/>
 <node id="4174201121" visible="true" version="2" changeset="60233132" timestamp="2018-06-28T02:51:15Z" user="Anton Khorev" uid="437809" lat="59.9354147" lon="30.3010845">
  <tag k="access" v="private"/>
  <tag k="barrier" v="gate"/>
 </node>
 <node id="4174201123" visible="true" version="4" changeset="109067490" timestamp="2021-08-03T06:16:44Z" user="mini-me" uid="3846961" lat="59.9354031" lon="30.3010461">
  <tag k="access" v="private"/>
  <tag k="addr:city" v="Санкт-Петербург"/>
  <tag k="addr:housenumber" v="1"/>
  <tag k="addr:street" v="Галерная улица"/>
  <tag k="entrance" v="service"/>
  <tag k="name" v="Служебная проходная"/>
 </node>
 <node id="5724836272" visible="true" version="3" changeset="70164753" timestamp="2019-05-12T16:25:40Z" user="mini-me" uid="3846961" lat="59.9356840" lon="30.3015658">
  <tag k="historic" v="memorial"/>
  <tag k="inscription" v="На этой площади (б. Сенатской) 14 (26) декабря 1825 года произошло восстание декабристов, первое в России вооруженное выступление против самодержавия"/>
  <tag k="memorial" v="plaque"/>
  <tag k="subject:wikidata" v="Q126306"/>
  <tag k="subject:wikipedia" v="ru:Восстание декабристов"/>
 </node>
 <node id="6003353090" visible="true" version="1" changeset="63736522" timestamp="2018-10-21T19:23:43Z" user="mini-me" uid="3846961" lat="59.9358473" lon="30.2999171"/>
 <node id="6003353091" visible="true" version="1" changeset="63736522" timestamp="2018-10-21T19:23:43Z" user="mini-me" uid="3846961" lat="59.9358304" lon="30.2998704"/>
 <node id="6003353092" visible="true" version="1" changeset="63736522" timestamp="2018-10-21T19:23:43Z" user="mini-me" uid="3846961" lat="59.9358796" lon="30.3001628"/>
 <node id="6003353093" visible="true" version="1" changeset="63736522" timestamp="2018-10-21T19:23:43Z" user="mini-me" uid="3846961" lat="59.9358495" lon="30.3002063"/>
 <node id="6003353094" visible="true" version="1" changeset="63736522" timestamp="2018-10-21T19:23:43Z" user="mini-me" uid="3846961" lat="59.9354671" lon="30.3004482"/>
 <node id="6003353095" visible="true" version="1" changeset="63736522" timestamp="2018-10-21T19:23:43Z" user="mini-me" uid="3846961" lat="59.9354488" lon="30.3003951"/>
 <!-- <way id="94946464" visible="true" version="1" changeset="6957401" timestamp="2011-01-13T14:00:51Z" user="KonTur" uid="43262">
  <nd ref="1102038477"/>
  <nd ref="1102038539"/>
  <nd ref="1102038360"/>
  <nd ref="1102038663"/>
  <nd ref="1102038194"/>
  <nd ref="1102038592"/>
  <nd ref="1102038279"/>
  <nd ref="1102038320"/>
  <nd ref="1102038231"/>
  <nd ref="1102038463"/>
  <nd ref="1102038390"/>
  <nd ref="1102038189"/>
  <nd ref="1102038294"/>
  <nd ref="1102038477"/>
 </way> -->
 <!-- <way id="94946474" visible="true" version="2" changeset="63736522" timestamp="2018-10-21T19:23:44Z" user="mini-me" uid="3846961">
  <nd ref="1102038256"/>
  <nd ref="1102038346"/>
  <nd ref="1102038298"/>
  <nd ref="1102038564"/>
  <nd ref="1102038258"/>
  <nd ref="1102038501"/>
  <nd ref="1102038481"/>
  <nd ref="1102038705"/>
  <nd ref="6003353095"/>
  <nd ref="6003353094"/>
  <nd ref="1102038256"/>
 </way> -->
 <way id="94946479" visible="true" version="11" changeset="62436801" timestamp="2018-09-09T23:31:46Z" user="Anton Khorev" uid="437809">
  <nd ref="1102038352"/>
  <nd ref="3625611709"/>
  <nd ref="1102038497"/>
  <nd ref="1102038469"/>
  <nd ref="1102038235"/>
  <nd ref="1102038192"/>
  <nd ref="1102038524"/>
  <nd ref="1606512665"/>
  <nd ref="3811443090"/>
  <nd ref="3811443091"/>
  <nd ref="5724836272"/>
  <nd ref="1102038640"/>
  <nd ref="3625629670"/>
  <nd ref="3625629684"/>
  <nd ref="3811443089"/>
  <nd ref="4174201121"/>
  <nd ref="4174201123"/>
  <nd ref="1102038188"/>
  <nd ref="1102038589"/>
  <nd ref="1102038430"/>
  <nd ref="1102038273"/>
  <nd ref="1102038352"/>
 </way>
 <!-- <way id="94946483" visible="true" version="2" changeset="63736522" timestamp="2018-10-21T19:23:44Z" user="mini-me" uid="3846961">
  <nd ref="1102038691"/>
  <nd ref="1102038238"/>
  <nd ref="1102038741"/>
  <nd ref="6003353092"/>
  <nd ref="6003353093"/>
  <nd ref="1102038434"/>
  <nd ref="1102038216"/>
  <nd ref="1102038526"/>
  <nd ref="6003353090"/>
  <nd ref="6003353091"/>
  <nd ref="1102038691"/>
 </way> -->
 <!-- <way id="94946490" visible="true" version="1" changeset="6957401" timestamp="2011-01-13T14:00:57Z" user="KonTur" uid="43262">
  <nd ref="1102038629"/>
  <nd ref="1102038411"/>
  <nd ref="1102038302"/>
  <nd ref="1102038697"/>
  <nd ref="1102038339"/>
  <nd ref="1102038621"/>
  <nd ref="1102038219"/>
  <nd ref="1102038441"/>
  <nd ref="1102038173"/>
  <nd ref="1102038394"/>
  <nd ref="1102038368"/>
  <nd ref="1102038729"/>
  <nd ref="1102038629"/>
 </way> -->
 <relation id="1374229" visible="true" version="15" changeset="148617517" timestamp="2024-03-14T00:18:37Z" user="mini-me" uid="3846961">
  <member type="way" ref="94946479" role="outer"/>
  <!-- <member type="way" ref="94946483" role="inner"/>
  <member type="way" ref="94946464" role="inner"/>
  <member type="way" ref="94946474" role="inner"/>
  <member type="way" ref="94946490" role="inner"/> -->
  <tag k="addr:housenumber" v="1"/>
  <tag k="addr:postcode" v="190000"/>
  <tag k="addr:street" v="Сенатская площадь"/>
  <tag k="architect" v="Карл Иванович Росси"/>
  <tag k="architect:wikidata" v="Q619584"/>
  <tag k="building" v="yes"/>
  <tag k="building:levels" v="4"/>
  <tag k="old_name" v="Здание Сената"/>
  <tag k="start_date" v="1834"/>
  <tag k="type" v="multipolygon"/>
  <tag k="wikidata" v="Q2269810"/>
 </relation>
</osm>
